.gitignore
.travis.yml
CHANGES.rst
CONTRIBUTORS.txt
MANIFEST.in
README.rst
bootstrap.py
buildout.cfg
icons.py
icons.txt
setup.py
travis.cfg
collective/__init__.py
collective.fontawesome.egg-info/PKG-INFO
collective.fontawesome.egg-info/SOURCES.txt
collective.fontawesome.egg-info/dependency_links.txt
collective.fontawesome.egg-info/entry_points.txt
collective.fontawesome.egg-info/namespace_packages.txt
collective.fontawesome.egg-info/not-zip-safe
collective.fontawesome.egg-info/requires.txt
collective.fontawesome.egg-info/top_level.txt
collective/fontawesome/__init__.py
collective/fontawesome/adapters.py
collective/fontawesome/configure.zcml
collective/fontawesome/interfaces.py
collective/fontawesome/testing.py
collective/fontawesome/upgrades.py
collective/fontawesome/upgrades.zcml
collective/fontawesome/example/__init__.py
collective/fontawesome/example/configure.zcml
collective/fontawesome/example/example.pt
collective/fontawesome/locales/collective.fontawesome.pot
collective/fontawesome/locales/rebuild.sh
collective/fontawesome/locales/es/LC_MESSAGES/collective.fontawesome.po
collective/fontawesome/profiles/default/cssregistry.xml
collective/fontawesome/profiles/default/metadata.xml
collective/fontawesome/profiles/plone5/registry.xml
collective/fontawesome/profiles/replace-plone-icons/browserlayer.xml
collective/fontawesome/profiles/replace-plone-icons/cssregistry.xml
collective/fontawesome/resources/css/font-awesome.css
collective/fontawesome/resources/css/font-awesome.min.css
collective/fontawesome/resources/css/replace-icons.css
collective/fontawesome/resources/webfonts/fa-brands-400.eot
collective/fontawesome/resources/webfonts/fa-brands-400.svg
collective/fontawesome/resources/webfonts/fa-brands-400.ttf
collective/fontawesome/resources/webfonts/fa-brands-400.woff
collective/fontawesome/resources/webfonts/fa-brands-400.woff2
collective/fontawesome/resources/webfonts/fa-regular-400.eot
collective/fontawesome/resources/webfonts/fa-regular-400.svg
collective/fontawesome/resources/webfonts/fa-regular-400.ttf
collective/fontawesome/resources/webfonts/fa-regular-400.woff
collective/fontawesome/resources/webfonts/fa-regular-400.woff2
collective/fontawesome/resources/webfonts/fa-solid-900.eot
collective/fontawesome/resources/webfonts/fa-solid-900.svg
collective/fontawesome/resources/webfonts/fa-solid-900.ttf
